gemcli
setup.cfg
setup.py
round/__init__.py
round/accounts.py
round/addresses.py
round/applications.py
round/client.py
round/config.py
round/developers.py
round/devices.py
round/errors.py
round/netki.py
round/networks.py
round/rules.py
round/subscriptions.py
round/transactions.py
round/users.py
round/wallets.py
round/wrappers.py
round.egg-info/PKG-INFO
round.egg-info/SOURCES.txt
round.egg-info/dependency_links.txt
round.egg-info/not-zip-safe
round.egg-info/pbr.json
round.egg-info/requires.txt
round.egg-info/top_level.txt
round/test/__init__.py