Metadata-Version: 1.0
Name: round
Version: 0.9.9
Summary: Python client for Gem.co
Home-page: http://github.com/GemHQ/round-py
Author: Matt Smith <matt@gem.co>, Dustin Laurence <dustin@gem.co>
Author-email: developers@gem.co
License: MIT
Platform: UNKNOWN
